popcorn/__init__.py
popcorn/api/api.py
popcorn/api/models/PersonApi.py
popcorn/api/models/Result.py
popcorn/api/models/SearchApi.py
popcorn/cli.py
popcorn/config.py
popcorn/controller.py
popcorn/dto.py
popcorn/models/AlsoWatched.py
popcorn/models/Content.py
popcorn/models/Creative.py
popcorn/models/Ios.py
popcorn/models/ItemMovie.py
popcorn/models/ItemShow.py
popcorn/models/Links.py
popcorn/models/ListingKey.py
popcorn/models/Metadata.py
popcorn/models/Person.py
popcorn/models/Rank.py
popcorn/models/RatingStats.py
popcorn/models/ReelgoodScores.py
popcorn/models/RegionalAvailability.py
popcorn/models/ScoreBreakdown.py
popcorn/models/Search.py
popcorn/models/Seasons.py
popcorn/models/SourceAdPlacement.py
popcorn/models/Streamability.py
popcorn/models/Tag.py
popcorn/models/Trailer.py
popcorn/models/TVShowEpisode.py
popcorn/tables/people.py
popcorn/tables/sources.py
popcorn/tables/table_details_movie.py
popcorn/tables/table_person.py
popcorn/tables/table_search.py
popcorn/tables/tableDetailsShow.py
popcorn/tables/TableInterface.py
popcorn/utils.py
popcornshow-0.1.7.dist-info/entry_points.txt
popcornshow-0.1.7.dist-info/LICENSE
popcornshow-0.1.7.dist-info/METADATA
popcornshow-0.1.7.dist-info/WHEEL
popcornshow-0.1.7.dist-info/RECORD
