Metadata-Version: 2.3
Name: popcornshow
Version: 0.1.7
Summary: Show information about movie and movies
License: Beerware
Author: Icaro Nunes
Author-email: icarornunes@gmail.com
Requires-Python: >=3.10,<4.0
Classifier: License :: Other/Proprietary License
Classifier: Programming Language :: Python :: 3
Classifier: Programming Language :: Python :: 3.10
Classifier: Programming Language :: Python :: 3.11
Classifier: Programming Language :: Python :: 3.12
Classifier: Programming Language :: Python :: 3.13
Classifier: Topic :: Utilities
Requires-Dist: click (==8.1.3)
Requires-Dist: requests (==2.31.0)
Requires-Dist: rich (==13.3.2)
Requires-Dist: typer (==0.7.0)
Requires-Dist: typer-cli (==0.0.13)
Project-URL: Bug Tracker, https://github.com/icaronunes/popcornshow-cli/actions
Project-URL: Cod, https://github.com/icaronunes/popcornshow-cli
Project-URL: Doc, https://popcornshow-cli.readthedocs.io/en/latest/
